math_mcp/__init__.py
math_mcp/server.py
math_mcp/visualization.py
math_mcp/persistence/__init__.py
math_mcp/persistence/models.py
math_mcp/persistence/storage.py
math_mcp/persistence/workspace.py
math_mcp_learning_server-0.10.3.dist-info/licenses/LICENSE
math_mcp_learning_server-0.10.3.dist-info/METADATA
math_mcp_learning_server-0.10.3.dist-info/WHEEL
math_mcp_learning_server-0.10.3.dist-info/entry_points.txt
math_mcp_learning_server-0.10.3.dist-info/top_level.txt
math_mcp_learning_server-0.10.3.dist-info/RECORD
