Metadata-Version: 2.4
Name: math-mcp-learning-server
Version: 0.10.3
Summary: Production-ready educational MCP server with enhanced visualizations and persistent workspace - Complete learning guide demonstrating FastMCP 2.0 best practices for Model Context Protocol development
Author-email: Hugues Clouâtre <hugues@linux.com>
License-Expression: MIT
Project-URL: Homepage, https://github.com/clouatre-labs/math-mcp-learning-server
Project-URL: Repository, https://github.com/clouatre-labs/math-mcp-learning-server
Project-URL: Issues, https://github.com/clouatre-labs/math-mcp-learning-server/issues
Project-URL: Documentation, https://github.com/clouatre-labs/math-mcp-learning-server#readme
Project-URL: Contributing, https://github.com/clouatre-labs/math-mcp-learning-server/blob/main/CONTRIBUTING.md
Project-URL: Roadmap, https://github.com/clouatre-labs/math-mcp-learning-server/blob/main/ROADMAP.md
Project-URL: Changelog, https://github.com/clouatre-labs/math-mcp-learning-server/releases
Project-URL: Code of Conduct, https://github.com/clouatre-labs/math-mcp-learning-server/blob/main/CODE_OF_CONDUCT.md
Project-URL: License, https://github.com/clouatre-labs/math-mcp-learning-server/blob/main/LICENSE
Keywords: mcp,math,calculator,learning,fastmcp,tutorial,education,cloud,deployment,workspace,persistence
Classifier: Development Status :: 4 - Beta
Classifier: Intended Audience :: Developers
Classifier: Intended Audience :: Education
Classifier: Programming Language :: Python :: 3.11
Classifier: Programming Language :: Python :: 3.14
Classifier: Topic :: Education
Classifier: Topic :: Software Development :: Libraries :: Application Frameworks
Classifier: Topic :: Scientific/Engineering :: Mathematics
Classifier: Topic :: Documentation
Classifier: Environment :: Console
Requires-Python: >=3.11
License-File: LICENSE
Requires-Dist: fastmcp>=2.0.0
Requires-Dist: pydantic>=2.12.0
Requires-Dist: pydantic-settings>=2.0.0
Provides-Extra: dev
Requires-Dist: pytest>=8.4.2; extra == "dev"
Requires-Dist: pytest-asyncio>=0.25.2; extra == "dev"
Requires-Dist: pytest-cov>=4.0.0; extra == "dev"
Requires-Dist: ruff>=0.13.1; extra == "dev"
Provides-Extra: plotting
Requires-Dist: matplotlib>=3.10.6; extra == "plotting"
Requires-Dist: numpy>=2.3.3; extra == "plotting"
Provides-Extra: scientific
Requires-Dist: numpy>=2.3.3; extra == "scientific"
Dynamic: license-file
